streamlit_fastselectbox/__init__.py
streamlit_fastselectbox/my_selectbox_example.py
streamlit_fastselectbox/frontend/build/asset-manifest.json
streamlit_fastselectbox/frontend/build/bootstrap.min.css
streamlit_fastselectbox/frontend/build/index.html
streamlit_fastselectbox/frontend/build/static/js/main.1ed3b846.js
streamlit_fastselectbox/frontend/build/static/js/main.1ed3b846.js.LICENSE.txt
streamlit_fastselectbox/frontend/build/static/js/main.1ed3b846.js.map
streamlit_fastselectbox-0.0.3.dist-info/LICENSE
streamlit_fastselectbox-0.0.3.dist-info/METADATA
streamlit_fastselectbox-0.0.3.dist-info/WHEEL
streamlit_fastselectbox-0.0.3.dist-info/top_level.txt
streamlit_fastselectbox-0.0.3.dist-info/RECORD
